dww_test/__about__.py
dww_test/__init__.py
dww_test/__main__.py
dww_test/dww_test.py
dww_test/dww_test.py~
dww_test-0.0.6.dist-info/METADATA
dww_test-0.0.6.dist-info/WHEEL
dww_test-0.0.6.dist-info/licenses/LICENSE.txt
dww_test-0.0.6.dist-info/RECORD
