Metadata-Version: 2.1
Name: dww-test
Version: 0.0.6
Summary: Hatch test project
Project-URL: Documentation, https://github.com/unknown/dww-test#readme
Project-URL: Issues, https://github.com/unknown/dww-test/issues
Project-URL: Source, https://github.com/unknown/dww-test
Author-email: "U.N. Owen" <void@some.where>
License-Expression: MIT
License-File: LICENSE.txt
Classifier: Development Status :: 4 - Beta
Classifier: Programming Language :: Python
Classifier: Programming Language :: Python :: 3.7
Classifier: Programming Language :: Python :: 3.8
Classifier: Programming Language :: Python :: 3.9
Classifier: Programming Language :: Python :: 3.10
Classifier: Programming Language :: Python :: 3.11
Classifier: Programming Language :: Python :: Implementation :: CPython
Classifier: Programming Language :: Python :: Implementation :: PyPy
Requires-Python: >=3.7
